aioidex/__init__.py
aioidex/datastream/__init__.py
aioidex/datastream/datastream.py
aioidex/datastream/sub_manager.py
aioidex/exceptions.py
aioidex/http/__init__.py
aioidex/http/client.py
aioidex/http/modules/base.py
aioidex/http/modules/public.py
aioidex/http/network.py
aioidex/tests/__init__.py
aioidex/tests/test_client.py
aioidex/tests/test_datastream.py
aioidex/tests/test_exceptions.py
aioidex/tests/test_network.py
aioidex/tests/test_public.py
aioidex/tests/test_subscription_manager.py
aioidex/tests/test_subscriptions.py
aioidex/types/events.py
aioidex/types/subscriptions.py
aioidex-0.3.0.dist-info/WHEEL
aioidex-0.3.0.dist-info/METADATA
aioidex-0.3.0.dist-info/RECORD
